{
  "alexa": 147,
  "crawls": [
    "theguardian.com/Privacy Policy.txt"
  ],
  "freesoftware": false,
  "fulltos": {},
  "id": 455,
  "keywords": [],
  "meta": {
    "spec-version": "1.1"
  },
  "name": "theguardian",
  "related": [],
  "slug": "theguardian",
  "tosback2": {
    "Privacy Policy": {
      "name": "Privacy Policy",
      "url": "https://www.theguardian.com/help/privacy-policy"
    }
  },
  "tosdr": {
    "rated": false
  },
  "type": "service",
  "url": "theguardian.com",
  "urls": [
    "theguardian.com"
  ]
}