{
  "date": {},
  "from": [
    {
      "address": "michiel@unhosted.org",
      "name": "Michiel de Jong"
    }
  ],
  "headers": {
    "content-type": "text/plain; charset=ISO-8859-1",
    "date": "Thu, 9 Aug 2012 13:23:06 +0200",
    "delivered-to": "michiel@unhosted.org",
    "from": "Michiel de Jong <michiel@unhosted.org>",
    "message-id": "<CA+aD3u2sr+TGsDHEXQtvyOHCg9qHGKLUkLYxMOdL29v+EQvfvg@mail.gmail.com>",
    "mime-version": "1.0",
    "received": "by 10.142.11.16 with HTTP; Thu, 9 Aug 2012 04:23:06 -0700 (PDT)",
    "subject": "eff tosback2",
    "to": "tosdr@googlegroups.com",
    "x-originating-ip": "[91.64.228.42]"
  },
  "messageId": "CA+aD3u2sr+TGsDHEXQtvyOHCg9qHGKLUkLYxMOdL29v+EQvfvg@mail.gmail.com",
  "priority": "normal",
  "receivedDate": {},
  "subject": "eff tosback2",
  "text": "fyi (also for the newcomers), here is the mailing list for the eff\ntosback2 project which will serve as our canonical data source for ToS\nand PP texts, and also to notify us when changes happen and services\nneed to be re-rated:\n\nhttps://mail1.eff.org/mailman/listinfo/tosback2\nhttps://mail1.eff.org/pipermail/tosback2/2012-August/thread.html\n\nTosback2 tracks ToS documents and publishes diffs in a\nmachine-readable format (in the form of a git repo basically) whenever\nthey change. This awesome project is run by EFF, and ToS;DR is only\none of the projects that benefit from it; for instance researchers who\nwant to write scientific studies about consumer rights online (can)\nalso use it.\n\n\nciao,\nMichiel\n",
  "to": [
    {
      "address": "tosdr@googlegroups.com",
      "name": ""
    }
  ]
}