{
  "id": "11086",
  "needModeration": false,
  "quoteDoc": "Privacy Policy",
  "quoteEnd": 12073,
  "quoteStart": 11687,
  "quoteText": "business partners, third party suppliers and our subcontractors (including delivery companies, payment providers and fraud prevention providers) to enable us to provide our services, operate our websites and app and to detect and prevent fraudulent transactions;</p>\n<p>(c)         analytics and search engine providers that assist us in the improvement and optimisation of our website;",
  "services": [
    "viagogo"
  ],
  "title": "This service can share your personal information to third parties ",
  "topics": [],
  "tosdr": {
    "binding": true,
    "case": "This service can share your personal information to third parties ",
    "tldr": "Generated through the annotate view"
  }
}