{
  "id": "5002",
  "needModeration": true,
  "services": [
    "frontendmasters"
  ],
  "title": "The service provides information about how they collect personal data",
  "topics": [],
  "tosdr": {
    "binding": true,
    "case": "The service provides information about how they collect personal data",
    "tldr": "Log\tInformation - When\tyou\tuse\tthe\tService\twe\tmay\tautomatically\tcollect\tand\tstore\t\r\ncertain\tinformation\tin\tserver\tlogs,\tsuch\tas\tIP\taddresses,\thardware\tsettings,\tbrowser\t\r\ntype,\tand\treferring\tURLs.\r\nLocal\tStorage - We\tmay\tcollect\tand\tstore\tinformation\tlocally\ton\tthe\tdevice\tyou\tuse\t\r\nto\taccess\tthe\tService,\tsuch\tas\tin\tweb\tbrowser\tstorage\tand\tapplication\tdata\tcaches.\r\nCookies\tand\tOther\tIdentifiers - We\tuse\tvarious\ttechnologies\tto\tcollect\tand\tstore\t\r\ninformation\twhen\tyou\tvisit\tthe\t"
  }
}