{
  "id": "6398",
  "needModeration": true,
  "quoteDoc": "Privacy Policy",
  "quoteEnd": 14839,
  "quoteStart": 14707,
  "quoteText": "the Airbnb Platform currently does not respond to a “Do Not Track” signal in the HTTP header from your browser or mobile application",
  "services": [
    "airbnb"
  ],
  "title": "This service ignores the Do Not Track (DNT) header and tracks users anyway even if they set this header.",
  "topics": [],
  "tosdr": {
    "binding": true,
    "case": "This service ignores the Do Not Track (DNT) header and tracks users anyway even if they set this header.",
    "tldr": "Generated through the annotate view"
  }
}