{
  "id": "8568",
  "needModeration": true,
  "quoteDoc": "Terms of Service",
  "quoteEnd": 12984,
  "quoteStart": 12830,
  "quoteText": "To the extent permitted by law, Cocoon reserves the right to use any data collected, explicitly or implicitly, in any form or fashion that Cocoon decides.",
  "services": [
    "virtualworldcomputingcocoonmydatarewards"
  ],
  "title": "This service uses your personal information for many different purposes",
  "topics": [],
  "tosdr": {
    "binding": true,
    "case": "This service uses your personal information for many different purposes",
    "tldr": "Generated through the annotate view"
  }
}