{
  "tosdr": {
    "tldr": "Generated through the annotate view",
    "case": "This service can delete your content if you violate the terms"
  },
  "id": "10039",
  "title": "This service can delete your content if you violate the terms",
  "quoteDoc": "End-User License Agreement",
  "quoteStart": 17957,
  "quoteEnd": 18188,
  "quoteText": "Turnitin reserves the right, but shall have no obligation to edit or remove any Communication, in whole or in part, that in Turnitin's sole discretion is objectionable, disruptive to the Site or in violation of this User Agreement.",
  "needModeration": true,
  "services": [
    "turnitin"
  ]
}