{
  "id": "10472",
  "needModeration": true,
  "quoteDoc": " Samsung Services Terms and Conditions",
  "quoteEnd": 24272,
  "quoteStart": 23932,
  "quoteText": "\n<b>SURVIVAL |</b> Any provisions within these Terms that by their nature should continue to be in effect, including without limitation the following Sections: License, Disclaimer of Warranty, Limitation of Liability, Indemnification and General, shall survive the expiration or termination of these Terms, and remain valid and binding.<br>",
  "services": [
    "samsung"
  ],
  "title": "defend, indemnify, hold harmless; survives termination",
  "topics": [],
  "tosdr": {
    "binding": true,
    "case": "defend, indemnify, hold harmless; survives termination",
    "tldr": "Generated through the annotate view"
  }
}