{
  "tosdr": {
    "tldr": "Generated through the annotate view",
    "case": "The service may use tracking pixels, web beacons, browser fingerprinting, and/or device fingerprinting on users."
  },
  "id": "10785",
  "title": "The service may use tracking pixels, web beacons, browser fingerprinting, and/or device fingerprinting on users.",
  "quoteDoc": "Privacy Policy",
  "quoteStart": 5476,
  "quoteEnd": 5624,
  "quoteText": "<li>unique device identifier (UDID) or mobile equipment identifier (MEID) for your mobile device;</li>\n<li>device and component serial numbers;</li>",
  "services": [
    "mcdonald's"
  ]
}