{
  "discussion": "https://groups.google.com/d/topic/tosdr/I3MgaNo1Plc/discussion",
  "id": "1084",
  "needModeration": true,
  "quoteDoc": "Privacy Statement",
  "quoteEnd": 5272,
  "quoteStart": 5198,
  "quoteText": "Send you product updates, marketing communication, and service information",
  "services": [
    "lastpass"
  ],
  "set": "set+service+and+topic",
  "slug": "I3MgaNo1Plc",
  "title": "No assurance of an opt-out method for non-transactional email",
  "topics": [
    "user-choice"
  ],
  "tosdr": {
    "binding": true,
    "case": "You cannot opt out of promotional communications",
    "tldr": "If you are a registered user of a LastPass website and have supplied your email address, LastPass may occasionally send you an email to tell you about new features, solicit your feedback, or just keep you up to date with what's going on with LastPass and their products. They expect to keep this type of email to a minimum."
  }
}