{
  "tosdr": {
    "tldr": "Generated through the annotate view",
    "irrelevant": true,
    "case": "Blocking first party cookies may limit your ability to use the service"
  },
  "id": "11316",
  "title": "Blocking first party cookies may limit your ability to use the service",
  "quoteDoc": "Privacy Policy",
  "quoteStart": 48955,
  "quoteEnd": 49235,
  "quoteText": "</p>\n<p>\n</p>\n<p>You have the right to decide whether to accept or reject&nbsp;cookies.\nIf you choose to set your web browser controls to reject cookies, you&nbsp;may still use our website though your access to some functionality and areas of<br>our website may be restricted.</p>",
  "services": [
    "aliexpress"
  ]
}