{
  "tosdr": {
    "tldr": "PERPETUAL LICENSE\r\nFull quote: \"By uploading, distributing, transmitting or otherwise using Your Content with the Service, you grant to us a perpetual, nonexclusive, transferable, royalty-free, sublicensable, and worldwide license to use, host, reproduce, modify, adapt, publish, translate, create derivative works from, distribute, perform, and display Your Content in connection with operating and providing the Service.\" ",
    "case": "This service keeps a license on user-generated content even after users close their accounts."
  },
  "id": "11416",
  "title": "This service keeps a license on user-generated content even after users close their accounts.",
  "quoteDoc": "Terms Of Service",
  "quoteStart": 8728,
  "quoteEnd": 8847,
  "quoteText": "By uploading, distributing, transmitting or otherwise using Your Content with the Service, you grant to us a perpetual,",
  "services": [
    "discord"
  ]
}