{
  "id": "11628",
  "quoteDoc": "Privacy Policy - other countries",
  "quoteEnd": 10260,
  "quoteStart": 10050,
  "quoteText": "We use cookies and other similar technologies (e.g.\nweb beacons, flash cookies, etc.) (“Cookies”) to enhance your experience using the Platform, improve our services, and provide you with targeted advertising .",
  "services": [
    "tiktok"
  ],
  "title": "The service may use tracking pixels, web beacons, browser fingerprinting, and/or device fingerprinting on users.",
  "topics": [

  ],
  "tosdr": {
    "binding": true,
    "case": "The service may use tracking pixels, web beacons, browser fingerprinting, and/or device fingerprinting on users.",
    "tldr": "Generated through the annotate view"
  }
}