{
  "tosdr": {
    "tldr": "Generated through the annotate view",
    "case": "This service is only available to users over a certain age"
  },
  "id": "12299",
  "title": "This service is only available to users over a certain age",
  "quoteDoc": "Legal",
  "quoteStart": 2069,
  "quoteEnd": 2221,
  "quoteText": "If you are under 13 years of age, you are not authorized to use the Service, with or without registering, and must stop use of the Service immediately.\n",
  "needModeration": true,
  "services": [
    "fivestars"
  ]
}