{
  "id": "12471",
  "needModeration": true,
  "quoteDoc": "Privacy Policy",
  "quoteEnd": 21533,
  "quoteStart": 20834,
  "quoteText": "<p>We use reasonable physical, electronic, and administrative safeguards to help us protect the security, integrity and confidentiality of data stored on our system.\nThe Site encrypts your credit card number and other Personal Information using secure socket layer (SSL) technology to provide for the secure transmission of the information from your PC to our servers.\nSSL is an industry-standard protocol for encryption over the Internet.\nWhile no system is 100% secure, we believe that the measures we have implemented minimize the risk of security breach to an appropriate level given the types of information involved.\nPlease note that any information you provide us by email is unencrypted.</p>",
  "services": [
    "artspace"
  ],
  "title": "The user is informed about security practices",
  "topics": [

  ],
  "tosdr": {
    "binding": true,
    "case": "The user is informed about security practices",
    "tldr": "Generated through the annotate view"
  }
}