{
  "tosdr": {
    "tldr": "Generated through the annotate view",
    "case": "Blocking first party cookies may limit your ability to use the service"
  },
  "id": "12623",
  "title": "Blocking first party cookies may limit your ability to use the service",
  "quoteDoc": "Privacy Policy",
  "quoteStart": 10166,
  "quoteEnd": 10354,
  "quoteText": "You can disable or decline some cookies for our sites and services.\nBut, since some parts of our service rely on cookies to work, those services could become difficult or impossible to use",
  "needModeration": true,
  "services": [
    "paypal"
  ]
}