{
  "tosdr": {
    "tldr": "Generated through the annotate view",
    "case": "You can opt out of promotional communications"
  },
  "id": "12842",
  "title": "You can opt out of promotional communications",
  "quoteDoc": "Terms of Service",
  "quoteStart": 12782,
  "quoteEnd": 12972,
  "quoteText": "To opt out of receiving communications from us via email, please email us at support@eightpoint.ky or click on the “unsubscribe” link at the bottom of any communication you receive from us.\n",
  "needModeration": true,
  "services": [
    "searchencrypt"
  ]
}