{
  "id": "4564",
  "needModeration": false,
  "quoteDoc": "Cookie Statement",
  "quoteEnd": 4494,
  "quoteStart": 4439,
  "quoteText": "Below is a full list of cookies set by www.amnesty.org ",
  "services": [
    "amnestyinternationallimited(uk)"
  ],
  "title": "The service provides a complete list of all cookies set by its website",
  "topics": [

  ],
  "tosdr": {
    "binding": true,
    "case": "The service provides a complete list of all cookies set by its website",
    "tldr": "Generated through the annotate view"
  }
}