{
  "id": "5474",
  "needModeration": false,
  "quoteDoc": "Terms of Service",
  "quoteEnd": 26822,
  "quoteStart": 26615,
  "quoteText": "RYVER AND ITS LICENSORS AND SUPPLIERS DO NOT WARRANT OR MAKE ANY REPRESENTATIONS REGARDING THE USE OR THE RESULTS OF THE USE OF THE SERVICE IN TERMS OF THEIR CORRECTNESS, ACCURACY, RELIABILITY, OR OTHERWISE.",
  "services": [
    "ryver"
  ],
  "title": "The service does not guarantee accuracy or reliability of the information provided",
  "topics": [],
  "tosdr": {
    "binding": true,
    "case": "The service does not guarantee accuracy or reliability of the information provided",
    "tldr": "Generated through the annotate view"
  }
}