{
  "id": "5841",
  "quoteDoc": "Privacy Policy",
  "quoteEnd": 6631,
  "quoteStart": 5818,
  "quoteText": "Your location information<p>We collect information about your location when you use our services, which helps us offer features like driving directions for your weekend getaway or showtimes for movies playing near you.</p>\n<p>Your location can be determined with varying degrees of accuracy by:</p>\n<ul>\n<li>GPS</li>\n<li>IP address</li>\n<li>Sensor data from your device</li>\n<li>Information about things near your device, such as Wi-Fi access points, cell towers, and Bluetooth-enabled devices</li>\n</ul>\n<p>The types of location data we collect depend in part on your device and account settings.\nFor example, you can turn your Android device’s location on or off using the device’s settings app.\nYou can also turn on Location History if you want to save and manage your location information in your account.</p>",
  "services": [
    "google"
  ],
  "title": "This service may collect, use, and share location data",
  "topics": [

  ],
  "tosdr": {
    "binding": true,
    "case": "This service may collect, use, and share location data",
    "tldr": "Generated through the annotate view"
  },
  "needModeration": true
}