{
  "id": "5864",
  "quoteDoc": "Política de Privacidade",
  "quoteEnd": 4613,
  "quoteStart": 4453,
  "quoteText": "Caso queira que apaguemos algum dado pessoal armazenado nesse site, envie um e-mail para adpd@protonmail.ch explicitando seu desejo e os dados a serem apagados.",
  "services": [
    "associaçãodedefesadaprivacidadedigital"
  ],
  "title": "The service provides a free help desk",
  "topics": [],
  "tosdr": {
    "binding": true,
    "case": "The service provides a free help desk",
    "irrelevant": true,
    "tldr": "Generated through the annotate view"
  }
}