{
  "id": "6359",
  "needModeration": false,
  "quoteDoc": "Data Use Policy",
  "quoteEnd": 7393,
  "quoteStart": 7203,
  "quoteText": "If we are going to release your information, our policy is to provide you with notice unless we are prohibited from doing so by law or court order (e.g., an order under 18 U.S.C.\nยง 2705(b)).",
  "services": [
    "openhumans"
  ],
  "title": "The service promises to inform and/or notify users regarding government inquiries that may involve users' personal data",
  "topics": [],
  "tosdr": {
    "binding": true,
    "case": "The service promises to inform and/or notify users regarding government inquiries that may involve users' personal data",
    "tldr": "Generated through the annotate view"
  }
}