{
  "id": "6691",
  "quoteDoc": "Terms of service",
  "quoteEnd": 16359,
  "quoteStart": 16290,
  "quoteText": "that the Service will be uninterrupted, timely, secure, or error-free",
  "services": [
    "bitwarden"
  ],
  "title": "The service provider makes no warranty regarding uninterrupted, timely, secure or error-free service",
  "topics": [

  ],
  "tosdr": {
    "binding": true,
    "case": "The service provider makes no warranty regarding uninterrupted, timely, secure or error-free service",
    "tldr": "From the Terms of Service, \"Bitwarden does not warrant that the Service ... will be uninterrupted, timely, secure, or error-free\""
  }
}