{
  "id": "6860",
  "needModeration": true,
  "quoteDoc": "Privacy Policy",
  "quoteEnd": 8118,
  "quoteStart": 8041,
  "quoteText": "Huawei will collect information about you from public and commercial sources.",
  "services": [
    "huawei"
  ],
  "title": "This service gathers information about you through third parties",
  "topics": [

  ],
  "tosdr": {
    "binding": true,
    "case": "This service gathers information about you through third parties",
    "tldr": "Generated through the annotate view"
  }
}