{
  "id": "6964",
  "quoteDoc": "Terms of Service",
  "quoteEnd": 20862,
  "quoteStart": 20370,
  "quoteText": "If you send us any submissions (e.g.\ne-mails, letters, postings to chat rooms, boards or&nbsp;contests), feedback, creative suggestions, ideas, notes, drawings, concepts or other&nbsp;information through the Vudu Service, your Vudu Account or any social media&nbsp;account Vudu may maintain from time to time (e.g., Twitter, Facebook, etc.)&nbsp;(collectively, Submissions”), they will be deemed to be our property and we will not be&nbsp;liable for any use or disclosure of such Submissions.",
  "services": [
    "vudu"
  ],
  "title": "If you offer suggestions to the service, they become the owner of the ideas that you give them",
  "topics": [],
  "tosdr": {
    "binding": true,
    "case": "If you offer suggestions to the service, they become the owner of the ideas that you give them",
    "tldr": "Generated through the annotate view"
  }
}