{
  "id": "7893",
  "quoteDoc": "Terms of Use",
  "quoteEnd": 3607,
  "quoteStart": 3214,
  "quoteText": "For content that is covered by intellectual property rights, like photos and videos (IP content), you specifically give us the following permission, subject to your privacy and application settings: you grant us a non-exclusive, transferable, sub-licensable, royalty-free, worldwide license to use any IP content that you post on or in connection with Facebook, Google or Twitter (IP License).",
  "services": [
    "speaky"
  ],
  "title": "The copyright license maintained by the service over user data and/or content is broader than necessary.",
  "topics": [],
  "tosdr": {
    "binding": true,
    "case": "The copyright license maintained by the service over user data and/or content is broader than necessary.",
    "tldr": "Generated through the annotate view"
  }
}