{
  "tosdr": {
    "tldr": "Generated through the annotate view",
    "case": "Features of the website are made available under a free software license"
  },
  "id": "7959",
  "title": "Features of the website are made available under a free software license",
  "quoteDoc": "Open Source",
  "quoteStart": 471,
  "quoteEnd": 666,
  "quoteText": "<p>Today, we are happy to take&nbsp;the next step and completely open source our webmail interface.\nThis means all the ProtonMail code that runs on your computer is now available for inspection.\n",
  "needModeration": true,
  "services": [
    "protonmail"
  ]
}