{
  "tosdr": {
    "tldr": "Generated through the annotate view",
    "case": "The service promises to inform and/or notify users regarding government inquiries that may involve users' personal data"
  },
  "id": "9045",
  "title": "The service promises to inform and/or notify users regarding government inquiries that may involve users' personal data",
  "quoteDoc": "Privacy Policy",
  "quoteStart": 10319,
  "quoteEnd": 10569,
  "quoteText": "We follow the law whenever we receive requests about you from a government or related to a lawsuit.\nWe will notify you when we are asked to hand over your personally identifiable information in this way unless we are legally prohibited from doing so.",
  "needModeration": true,
  "services": [
    "pocket"
  ]
}