{
  "tosdr": {
    "tldr": "Generated through the annotate view",
    "case": "Users agree not to submit illegal content"
  },
  "id": "9872",
  "title": "Users agree not to submit illegal content",
  "quoteDoc": "Terms and Conditions",
  "quoteStart": 4425,
  "quoteEnd": 4613,
  "quoteText": "You can't post any content that would be illegal to distribute under United States law, and we may be legally and morally obligated to report such uses to the authorities in certain cases.",
  "services": [
    "lib-reviews"
  ]
}